my_tool_package/__init__.py
my_tool_package/connections.py
my_tool_package/tools/__init__.py
my_tool_package/tools/my_tool_1.py
my_tool_package/tools/my_tool_2.py
my_tool_package/tools/utils.py
my_tool_package/yamls/my_tool_1.yaml
my_tool_package/yamls/my_tool_2.yaml
tests/__init__.py
tests/test_my_tool_1.py
tests/test_my_tool_2.py
my_tools_package_with_cstc-0.0.6.dist-info/METADATA
my_tools_package_with_cstc-0.0.6.dist-info/WHEEL
my_tools_package_with_cstc-0.0.6.dist-info/entry_points.txt
my_tools_package_with_cstc-0.0.6.dist-info/top_level.txt
my_tools_package_with_cstc-0.0.6.dist-info/RECORD
