Metadata-Version: 2.1
Name: my-tools-package-with-cstc
Version: 0.0.6
Summary: This is my tools package
